deephaven/ui/__init__.py
deephaven/ui/_register.py
deephaven/ui/_internal/EventContext.py
deephaven/ui/_internal/NoContextException.py
deephaven/ui/_internal/RenderContext.py
deephaven/ui/_internal/__init__.py
deephaven/ui/_internal/utils.py
deephaven/ui/_js/LICENSE
deephaven/ui/_js/package.json
deephaven/ui/_js/dist/index.js
deephaven/ui/components/__init__.py
deephaven/ui/components/accordion.py
deephaven/ui/components/action_button.py
deephaven/ui/components/action_group.py
deephaven/ui/components/action_menu.py
deephaven/ui/components/avatar.py
deephaven/ui/components/badge.py
deephaven/ui/components/basic.py
deephaven/ui/components/breadcrumbs.py
deephaven/ui/components/button.py
deephaven/ui/components/button_group.py
deephaven/ui/components/calendar.py
deephaven/ui/components/checkbox.py
deephaven/ui/components/checkbox_group.py
deephaven/ui/components/color_editor.py
deephaven/ui/components/color_picker.py
deephaven/ui/components/column.py
deephaven/ui/components/combo_box.py
deephaven/ui/components/content.py
deephaven/ui/components/contextual_help.py
deephaven/ui/components/contextual_help_trigger.py
deephaven/ui/components/dashboard.py
deephaven/ui/components/date_field.py
deephaven/ui/components/date_picker.py
deephaven/ui/components/date_range_picker.py
deephaven/ui/components/dialog.py
deephaven/ui/components/dialog_trigger.py
deephaven/ui/components/disclosure.py
deephaven/ui/components/disclosure_panel.py
deephaven/ui/components/disclosure_title.py
deephaven/ui/components/divider.py
deephaven/ui/components/flex.py
deephaven/ui/components/footer.py
deephaven/ui/components/form.py
deephaven/ui/components/fragment.py
deephaven/ui/components/grid.py
deephaven/ui/components/heading.py
deephaven/ui/components/html.py
deephaven/ui/components/icon.py
deephaven/ui/components/illustrated_message.py
deephaven/ui/components/image.py
deephaven/ui/components/inline_alert.py
deephaven/ui/components/item.py
deephaven/ui/components/item_table_source.py
deephaven_plugin_ui-0.32.1.dist-info/licenses/LICENSE
deephaven_plugin_ui-0.32.1.dist-info/METADATA
deephaven_plugin_ui-0.32.1.dist-info/WHEEL
deephaven_plugin_ui-0.32.1.dist-info/entry_points.txt
deephaven_plugin_ui-0.32.1.dist-info/top_level.txt
deephaven_plugin_ui-0.32.1.dist-info/RECORD
