Metadata-Version: 2.4
Name: deephaven-plugin-ui
Version: 0.32.1
Summary: deephaven.ui plugin
Home-page: https://github.com/deephaven/deephaven-plugins
Author: Deephaven Data Labs
Author-email: support@deephaven.io
Project-URL: Source Code, https://github.com/deephaven/deephaven-plugins
Project-URL: Bug Tracker, https://github.com/deephaven/deephaven-plugins/issues
Keywords: deephaven,plugin,graph
Platform: any
Classifier: Programming Language :: Python :: 3
Classifier: License :: OSI Approved :: Apache Software License
Classifier: Operating System :: OS Independent
Classifier: Environment :: Plugins
Classifier: Topic :: Scientific/Engineering :: Visualization
Classifier: Development Status :: 3 - Alpha
License-File: LICENSE
Requires-Dist: deephaven-core>=0.39.6
Requires-Dist: deephaven-plugin>=0.6.0
Requires-Dist: json-rpc~=1.15.0
Requires-Dist: pyjsonpatch~=0.1.3
Requires-Dist: deephaven-plugin-utilities>=0.0.2
Requires-Dist: typing_extensions; python_version < "3.11"
Requires-Dist: puremagic
Dynamic: license-file
